akuire/__init__.py
akuire/acquisition.py
akuire/assets/big.jpg
akuire/assets/utils.py
akuire/compilers/__init__.py
akuire/compilers/default.py
akuire/composition/__init__.py
akuire/composition/composer.py
akuire/composition/helpers.py
akuire/config.py
akuire/engine.py
akuire/errors.py
akuire/events/__init__.py
akuire/events/data_event.py
akuire/events/manager_event.py
akuire/helpers/__init__.py
akuire/helpers/base.py
akuire/managers/__init__.py
akuire/managers/base.py
akuire/managers/generic/delay.py
akuire/managers/rest/rest_manager.py
akuire/managers/testing/__init__.py
akuire/managers/testing/errors.py
akuire/managers/testing/faulty_camera.py
akuire/managers/testing/non_sweepable.py
akuire/managers/testing/stage.py
akuire/managers/testing/sweepable.py
akuire/managers/testing/zstage.py
akuire/managers/virtual/smlm_microscope.py
akuire/managers/virtual/virtual_microscope.py
akuire/vars.py
akuire-0.1.2.dist-info/METADATA
akuire-0.1.2.dist-info/WHEEL
akuire-0.1.2.dist-info/entry_points.txt
akuire-0.1.2.dist-info/RECORD
