Metadata-Version: 2.1
Name: akuire
Version: 0.1.2
Summary: 
Author: jhnnsrs
Author-email: jhnnsrs@gmail.com
Requires-Python: >=3.10,<4.0
Classifier: Programming Language :: Python :: 3
Classifier: Programming Language :: Python :: 3.10
Classifier: Programming Language :: Python :: 3.11
Classifier: Programming Language :: Python :: 3.12
Requires-Dist: aiohttp (>=3.9.5,<4.0.0)
Requires-Dist: koil (>=0.3.6,<0.4.0)
